{".class":"MypyFile","_fullname":"ezdxf.entities.blockrecord","future_import_flags":["annotations"],"is_partial_stub_package":false,"is_stub":false,"names":{".class":"SymbolTable","AbstractTagWriter":{".class":"SymbolTableNode","cross_ref":"ezdxf.lldxf.tagwriter.AbstractTagWriter","kind":"Gdef","module_hidden":true,"module_public":false},"Auditor":{".class":"SymbolTableNode","cross_ref":"ezdxf.audit.Auditor","kind":"Gdef","module_hidden":true,"module_public":false},"Block":{".class":"SymbolTableNode","cross_ref":"ezdxf.entities.block.Block","kind":"Gdef","module_hidden":true,"module_public":false},"BlockLayout":{".class":"SymbolTableNode","cross_ref":"ezdxf.layouts.blocklayout.BlockLayout","kind":"Gdef","module_hidden":true,"module_public":false},"BlockRecord":{".class":"SymbolTableNode","kind":"Gdef","node":{".class":"TypeInfo","_promote":[],"abstract_attributes":[],"alt_promote":null,"bases":["ezdxf.entities.dxfentity.DXFEntity"],"dataclass_transform_spec":null,"declared_metaclass":null,"defn":{".class":"ClassDef","fullname":"ezdxf.entities.blockrecord.BlockRecord","name":"BlockRecord","type_vars":[]},"deletable_attributes":[],"deprecated":null,"flags":[],"fullname":"ezdxf.entities.blockrecord.BlockRecord","has_param_spec_type":false,"metaclass_type":null,"metadata":{},"module_name":"ezdxf.entities.blockrecord","mro":["ezdxf.entities.blockrecord.BlockRecord","ezdxf.entities.dxfentity.DXFEntity","builtins.object"],"names":{".class":"SymbolTable","DXFATTRIBS":{".class":"SymbolTableNode","kind":"Mdef","node":{".class":"Var","flags":["is_initialized_in_class","is_inferred","has_explicit_value"],"fullname":"ezdxf.entities.blockrecord.BlockRecord.DXFATTRIBS","name":"DXFATTRIBS","setter_type":null,"type":"ezdxf.lldxf.attributes.DXFAttributes"}},"DXFTYPE":{".class":"SymbolTableNode","kind":"Mdef","node":{".class":"Var","flags":["is_initialized_in_class","is_inferred","has_explicit_value"],"fullname":"ezdxf.entities.blockrecord.BlockRecord.DXFTYPE","name":"DXFTYPE","setter_type":null,"type":"builtins.str"}},"__init__":{".class":"SymbolTableNode","kind":"Mdef","node":{".class":"FuncDef","abstract_status":0,"arg_kinds":[0],"arg_names":["self"],"dataclass_transform_spec":null,"deprecated":null,"flags":["is_trivial_self"],"fullname":"ezdxf.entities.blockrecord.BlockRecord.__init__","name":"__init__","type":{".class":"CallableType","arg_kinds":[0],"arg_names":["self"],"arg_types":["ezdxf.entities.blockrecord.BlockRecord"],"def_extras":{"first_arg":"self"},"fallback":"builtins.function","from_concatenate":false,"implicit":false,"imprecise_arg_kinds":false,"is_bound":false,"is_ellipsis_args":false,"name":"__init__ of BlockRecord","ret_type":{".class":"NoneType"},"type_guard":null,"type_is":null,"unpack_kwargs":false,"variables":[]}}},"add_entity":{".class":"SymbolTableNode","kind":"Mdef","node":{".class":"FuncDef","abstract_status":0,"arg_kinds":[0,0],"arg_names":["self","entity"],"dataclass_transform_spec":null,"deprecated":null,"flags":["is_trivial_self"],"fullname":"ezdxf.entities.blockrecord.BlockRecord.add_entity","name":"add_entity","type":{".class":"CallableType","arg_kinds":[0,0],"arg_names":["self","entity"],"arg_types":["ezdxf.entities.blockrecord.BlockRecord","ezdxf.entities.dxfgfx.DXFGraphic"],"def_extras":{"first_arg":"self"},"fallback":"builtins.function","from_concatenate":false,"implicit":false,"imprecise_arg_kinds":false,"is_bound":false,"is_ellipsis_args":false,"name":"add_entity of BlockRecord","ret_type":{".class":"NoneType"},"type_guard":null,"type_is":null,"unpack_kwargs":false,"variables":[]}}},"audit":{".class":"SymbolTableNode","kind":"Mdef","node":{".class":"FuncDef","abstract_status":0,"arg_kinds":[0,0],"arg_names":["self","auditor"],"dataclass_transform_spec":null,"deprecated":null,"flags":["is_trivial_self"],"fullname":"ezdxf.entities.blockrecord.BlockRecord.audit","name":"audit","type":{".class":"CallableType","arg_kinds":[0,0],"arg_names":["self","auditor"],"arg_types":["ezdxf.entities.blockrecord.BlockRecord","ezdxf.audit.Auditor"],"def_extras":{"first_arg":"self"},"fallback":"builtins.function","from_concatenate":false,"implicit":false,"imprecise_arg_kinds":false,"is_bound":false,"is_ellipsis_args":false,"name":"audit of BlockRecord","ret_type":{".class":"NoneType"},"type_guard":null,"type_is":null,"unpack_kwargs":false,"variables":[]}}},"block":{".class":"SymbolTableNode","implicit":true,"kind":"Mdef","node":{".class":"Var","flags":["explicit_self_type","is_ready","is_inferred"],"fullname":"ezdxf.entities.blockrecord.BlockRecord.block","name":"block","setter_type":null,"type":{".class":"UnionType","items":["ezdxf.entities.block.Block",{".class":"NoneType"}],"uses_pep604_syntax":false}}},"block_layout":{".class":"SymbolTableNode","implicit":true,"kind":"Mdef","node":{".class":"Var","flags":["explicit_self_type","is_ready","is_inferred"],"fullname":"ezdxf.entities.blockrecord.BlockRecord.block_layout","name":"block_layout","setter_type":null,"type":{".class":"UnionType","items":["ezdxf.layouts.blocklayout.BlockLayout",{".class":"NoneType"}],"uses_pep604_syntax":false}}},"delete_entity":{".class":"SymbolTableNode","kind":"Mdef","node":{".class":"FuncDef","abstract_status":0,"arg_kinds":[0,0],"arg_names":["self","entity"],"dataclass_transform_spec":null,"deprecated":null,"flags":["is_trivial_self"],"fullname":"ezdxf.entities.blockrecord.BlockRecord.delete_entity","name":"delete_entity","type":{".class":"CallableType","arg_kinds":[0,0],"arg_names":["self","entity"],"arg_types":["ezdxf.entities.blockrecord.BlockRecord","ezdxf.entities.dxfgfx.DXFGraphic"],"def_extras":{"first_arg":"self"},"fallback":"builtins.function","from_concatenate":false,"implicit":false,"imprecise_arg_kinds":false,"is_bound":false,"is_ellipsis_args":false,"name":"delete_entity of BlockRecord","ret_type":{".class":"NoneType"},"type_guard":null,"type_is":null,"unpack_kwargs":false,"variables":[]}}},"destroy":{".class":"SymbolTableNode","kind":"Mdef","node":{".class":"FuncDef","abstract_status":0,"arg_kinds":[0],"arg_names":["self"],"dataclass_transform_spec":null,"deprecated":null,"flags":[],"fullname":"ezdxf.entities.blockrecord.BlockRecord.destroy","name":"destroy","type":null}},"endblk":{".class":"SymbolTableNode","implicit":true,"kind":"Mdef","node":{".class":"Var","flags":["explicit_self_type","is_ready","is_inferred"],"fullname":"ezdxf.entities.blockrecord.BlockRecord.endblk","name":"endblk","setter_type":null,"type":{".class":"UnionType","items":["ezdxf.entities.block.EndBlk",{".class":"NoneType"}],"uses_pep604_syntax":false}}},"entity_space":{".class":"SymbolTableNode","implicit":true,"kind":"Mdef","node":{".class":"Var","flags":["is_inferred"],"fullname":"ezdxf.entities.blockrecord.BlockRecord.entity_space","name":"entity_space","setter_type":null,"type":"ezdxf.entitydb.EntitySpace"}},"export_block_definition":{".class":"SymbolTableNode","kind":"Mdef","node":{".class":"FuncDef","abstract_status":0,"arg_kinds":[0,0],"arg_names":["self","tagwriter"],"dataclass_transform_spec":null,"deprecated":null,"flags":["is_trivial_self"],"fullname":"ezdxf.entities.blockrecord.BlockRecord.export_block_definition","name":"export_block_definition","type":{".class":"CallableType","arg_kinds":[0,0],"arg_names":["self","tagwriter"],"arg_types":["ezdxf.entities.blockrecord.BlockRecord","ezdxf.lldxf.tagwriter.AbstractTagWriter"],"def_extras":{"first_arg":"self"},"fallback":"builtins.function","from_concatenate":false,"implicit":false,"imprecise_arg_kinds":false,"is_bound":false,"is_ellipsis_args":false,"name":"export_block_definition of BlockRecord","ret_type":{".class":"NoneType"},"type_guard":null,"type_is":null,"unpack_kwargs":false,"variables":[]}}},"export_entity":{".class":"SymbolTableNode","kind":"Mdef","node":{".class":"FuncDef","abstract_status":0,"arg_kinds":[0,0],"arg_names":["self","tagwriter"],"dataclass_transform_spec":null,"deprecated":null,"flags":["is_trivial_self"],"fullname":"ezdxf.entities.blockrecord.BlockRecord.export_entity","name":"export_entity","type":{".class":"CallableType","arg_kinds":[0,0],"arg_names":["self","tagwriter"],"arg_types":["ezdxf.entities.blockrecord.BlockRecord","ezdxf.lldxf.tagwriter.AbstractTagWriter"],"def_extras":{"first_arg":"self"},"fallback":"builtins.function","from_concatenate":false,"implicit":false,"imprecise_arg_kinds":false,"is_bound":false,"is_ellipsis_args":false,"name":"export_entity of BlockRecord","ret_type":{".class":"NoneType"},"type_guard":null,"type_is":null,"unpack_kwargs":false,"variables":[]}}},"is_active_paperspace":{".class":"SymbolTableNode","kind":"Mdef","node":{".class":"Decorator","func":{".class":"FuncDef","abstract_status":0,"arg_kinds":[0],"arg_names":["self"],"dataclass_transform_spec":null,"deprecated":null,"flags":["is_property","is_decorated","is_trivial_self"],"fullname":"ezdxf.entities.blockrecord.BlockRecord.is_active_paperspace","name":"is_active_paperspace","type":{".class":"CallableType","arg_kinds":[0],"arg_names":["self"],"arg_types":["ezdxf.entities.blockrecord.BlockRecord"],"def_extras":{"first_arg":"self"},"fallback":"builtins.function","from_concatenate":false,"implicit":false,"imprecise_arg_kinds":false,"is_bound":false,"is_ellipsis_args":false,"name":"is_active_paperspace of BlockRecord","ret_type":"builtins.bool","type_guard":null,"type_is":null,"unpack_kwargs":false,"variables":[]}},"is_overload":false,"var":{".class":"Var","flags":["is_initialized_in_class","is_property","is_ready","is_inferred"],"fullname":"ezdxf.entities.blockrecord.BlockRecord.is_active_paperspace","name":"is_active_paperspace","setter_type":null,"type":{".class":"CallableType","arg_kinds":[0],"arg_names":["self"],"arg_types":["ezdxf.entities.blockrecord.BlockRecord"],"def_extras":{"first_arg":"self"},"fallback":"builtins.function","from_concatenate":false,"implicit":false,"imprecise_arg_kinds":false,"is_bound":false,"is_ellipsis_args":false,"name":"is_active_paperspace of BlockRecord","ret_type":"builtins.bool","type_guard":null,"type_is":null,"unpack_kwargs":false,"variables":[]}}}},"is_any_layout":{".class":"SymbolTableNode","kind":"Mdef","node":{".class":"Decorator","func":{".class":"FuncDef","abstract_status":0,"arg_kinds":[0],"arg_names":["self"],"dataclass_transform_spec":null,"deprecated":null,"flags":["is_property","is_decorated","is_trivial_self"],"fullname":"ezdxf.entities.blockrecord.BlockRecord.is_any_layout","name":"is_any_layout","type":{".class":"CallableType","arg_kinds":[0],"arg_names":["self"],"arg_types":["ezdxf.entities.blockrecord.BlockRecord"],"def_extras":{"first_arg":"self"},"fallback":"builtins.function","from_concatenate":false,"implicit":false,"imprecise_arg_kinds":false,"is_bound":false,"is_ellipsis_args":false,"name":"is_any_layout of BlockRecord","ret_type":"builtins.bool","type_guard":null,"type_is":null,"unpack_kwargs":false,"variables":[]}},"is_overload":false,"var":{".class":"Var","flags":["is_initialized_in_class","is_property","is_ready","is_inferred"],"fullname":"ezdxf.entities.blockrecord.BlockRecord.is_any_layout","name":"is_any_layout","setter_type":null,"type":{".class":"CallableType","arg_kinds":[0],"arg_names":["self"],"arg_types":["ezdxf.entities.blockrecord.BlockRecord"],"def_extras":{"first_arg":"self"},"fallback":"builtins.function","from_concatenate":false,"implicit":false,"imprecise_arg_kinds":false,"is_bound":false,"is_ellipsis_args":false,"name":"is_any_layout of BlockRecord","ret_type":"builtins.bool","type_guard":null,"type_is":null,"unpack_kwargs":false,"variables":[]}}}},"is_any_paperspace":{".class":"SymbolTableNode","kind":"Mdef","node":{".class":"Decorator","func":{".class":"FuncDef","abstract_status":0,"arg_kinds":[0],"arg_names":["self"],"dataclass_transform_spec":null,"deprecated":null,"flags":["is_property","is_decorated","is_trivial_self"],"fullname":"ezdxf.entities.blockrecord.BlockRecord.is_any_paperspace","name":"is_any_paperspace","type":{".class":"CallableType","arg_kinds":[0],"arg_names":["self"],"arg_types":["ezdxf.entities.blockrecord.BlockRecord"],"def_extras":{"first_arg":"self"},"fallback":"builtins.function","from_concatenate":false,"implicit":false,"imprecise_arg_kinds":false,"is_bound":false,"is_ellipsis_args":false,"name":"is_any_paperspace of BlockRecord","ret_type":"builtins.bool","type_guard":null,"type_is":null,"unpack_kwargs":false,"variables":[]}},"is_overload":false,"var":{".class":"Var","flags":["is_initialized_in_class","is_property","is_ready","is_inferred"],"fullname":"ezdxf.entities.blockrecord.BlockRecord.is_any_paperspace","name":"is_any_paperspace","setter_type":null,"type":{".class":"CallableType","arg_kinds":[0],"arg_names":["self"],"arg_types":["ezdxf.entities.blockrecord.BlockRecord"],"def_extras":{"first_arg":"self"},"fallback":"builtins.function","from_concatenate":false,"implicit":false,"imprecise_arg_kinds":false,"is_bound":false,"is_ellipsis_args":false,"name":"is_any_paperspace of BlockRecord","ret_type":"builtins.bool","type_guard":null,"type_is":null,"unpack_kwargs":false,"variables":[]}}}},"is_block_layout":{".class":"SymbolTableNode","kind":"Mdef","node":{".class":"Decorator","func":{".class":"FuncDef","abstract_status":0,"arg_kinds":[0],"arg_names":["self"],"dataclass_transform_spec":null,"deprecated":null,"flags":["is_property","is_decorated","is_trivial_self"],"fullname":"ezdxf.entities.blockrecord.BlockRecord.is_block_layout","name":"is_block_layout","type":{".class":"CallableType","arg_kinds":[0],"arg_names":["self"],"arg_types":["ezdxf.entities.blockrecord.BlockRecord"],"def_extras":{"first_arg":"self"},"fallback":"builtins.function","from_concatenate":false,"implicit":false,"imprecise_arg_kinds":false,"is_bound":false,"is_ellipsis_args":false,"name":"is_block_layout of BlockRecord","ret_type":"builtins.bool","type_guard":null,"type_is":null,"unpack_kwargs":false,"variables":[]}},"is_overload":false,"var":{".class":"Var","flags":["is_initialized_in_class","is_property","is_ready","is_inferred"],"fullname":"ezdxf.entities.blockrecord.BlockRecord.is_block_layout","name":"is_block_layout","setter_type":null,"type":{".class":"CallableType","arg_kinds":[0],"arg_names":["self"],"arg_types":["ezdxf.entities.blockrecord.BlockRecord"],"def_extras":{"first_arg":"self"},"fallback":"builtins.function","from_concatenate":false,"implicit":false,"imprecise_arg_kinds":false,"is_bound":false,"is_ellipsis_args":false,"name":"is_block_layout of BlockRecord","ret_type":"builtins.bool","type_guard":null,"type_is":null,"unpack_kwargs":false,"variables":[]}}}},"is_modelspace":{".class":"SymbolTableNode","kind":"Mdef","node":{".class":"Decorator","func":{".class":"FuncDef","abstract_status":0,"arg_kinds":[0],"arg_names":["self"],"dataclass_transform_spec":null,"deprecated":null,"flags":["is_property","is_decorated","is_trivial_self"],"fullname":"ezdxf.entities.blockrecord.BlockRecord.is_modelspace","name":"is_modelspace","type":{".class":"CallableType","arg_kinds":[0],"arg_names":["self"],"arg_types":["ezdxf.entities.blockrecord.BlockRecord"],"def_extras":{"first_arg":"self"},"fallback":"builtins.function","from_concatenate":false,"implicit":false,"imprecise_arg_kinds":false,"is_bound":false,"is_ellipsis_args":false,"name":"is_modelspace of BlockRecord","ret_type":"builtins.bool","type_guard":null,"type_is":null,"unpack_kwargs":false,"variables":[]}},"is_overload":false,"var":{".class":"Var","flags":["is_initialized_in_class","is_property","is_ready","is_inferred"],"fullname":"ezdxf.entities.blockrecord.BlockRecord.is_modelspace","name":"is_modelspace","setter_type":null,"type":{".class":"CallableType","arg_kinds":[0],"arg_names":["self"],"arg_types":["ezdxf.entities.blockrecord.BlockRecord"],"def_extras":{"first_arg":"self"},"fallback":"builtins.function","from_concatenate":false,"implicit":false,"imprecise_arg_kinds":false,"is_bound":false,"is_ellipsis_args":false,"name":"is_modelspace of BlockRecord","ret_type":"builtins.bool","type_guard":null,"type_is":null,"unpack_kwargs":false,"variables":[]}}}},"is_xref":{".class":"SymbolTableNode","kind":"Mdef","node":{".class":"Decorator","func":{".class":"FuncDef","abstract_status":0,"arg_kinds":[0],"arg_names":["self"],"dataclass_transform_spec":null,"deprecated":null,"flags":["is_property","is_decorated","is_trivial_self"],"fullname":"ezdxf.entities.blockrecord.BlockRecord.is_xref","name":"is_xref","type":{".class":"CallableType","arg_kinds":[0],"arg_names":["self"],"arg_types":["ezdxf.entities.blockrecord.BlockRecord"],"def_extras":{"first_arg":"self"},"fallback":"builtins.function","from_concatenate":false,"implicit":false,"imprecise_arg_kinds":false,"is_bound":false,"is_ellipsis_args":false,"name":"is_xref of BlockRecord","ret_type":"builtins.bool","type_guard":null,"type_is":null,"unpack_kwargs":false,"variables":[]}},"is_overload":false,"var":{".class":"Var","flags":["is_initialized_in_class","is_property","is_ready","is_inferred"],"fullname":"ezdxf.entities.blockrecord.BlockRecord.is_xref","name":"is_xref","setter_type":null,"type":{".class":"CallableType","arg_kinds":[0],"arg_names":["self"],"arg_types":["ezdxf.entities.blockrecord.BlockRecord"],"def_extras":{"first_arg":"self"},"fallback":"builtins.function","from_concatenate":false,"implicit":false,"imprecise_arg_kinds":false,"is_bound":false,"is_ellipsis_args":false,"name":"is_xref of BlockRecord","ret_type":"builtins.bool","type_guard":null,"type_is":null,"unpack_kwargs":false,"variables":[]}}}},"load_dxf_attribs":{".class":"SymbolTableNode","kind":"Mdef","node":{".class":"FuncDef","abstract_status":0,"arg_kinds":[0,1],"arg_names":["self","processor"],"dataclass_transform_spec":null,"deprecated":null,"flags":["is_trivial_self"],"fullname":"ezdxf.entities.blockrecord.BlockRecord.load_dxf_attribs","name":"load_dxf_attribs","type":{".class":"CallableType","arg_kinds":[0,1],"arg_names":["self","processor"],"arg_types":["ezdxf.entities.blockrecord.BlockRecord",{".class":"UnionType","items":["ezdxf.entities.dxfns.SubclassProcessor",{".class":"NoneType"}],"uses_pep604_syntax":false}],"def_extras":{"first_arg":"self"},"fallback":"builtins.function","from_concatenate":false,"implicit":false,"imprecise_arg_kinds":false,"is_bound":false,"is_ellipsis_args":false,"name":"load_dxf_attribs of BlockRecord","ret_type":"ezdxf.entities.dxfns.DXFNamespace","type_guard":null,"type_is":null,"unpack_kwargs":false,"variables":[]}}},"map_resources":{".class":"SymbolTableNode","kind":"Mdef","node":{".class":"FuncDef","abstract_status":0,"arg_kinds":[0,0,0],"arg_names":["self","clone","mapping"],"dataclass_transform_spec":null,"deprecated":null,"flags":[],"fullname":"ezdxf.entities.blockrecord.BlockRecord.map_resources","name":"map_resources","type":{".class":"CallableType","arg_kinds":[0,0,0],"arg_names":["self","clone","mapping"],"arg_types":[{".class":"TypeVarType","default":{".class":"AnyType","missing_import_name":null,"source_any":null,"type_of_any":4},"fullname":"ezdxf.entities.blockrecord.BlockRecord.Self","id":0,"name":"Self","namespace":"","upper_bound":"ezdxf.entities.blockrecord.BlockRecord","values":[],"variance":0},{".class":"TypeVarType","default":{".class":"AnyType","missing_import_name":null,"source_any":null,"type_of_any":4},"fullname":"ezdxf.entities.blockrecord.BlockRecord.Self","id":0,"name":"Self","namespace":"","upper_bound":"ezdxf.entities.blockrecord.BlockRecord","values":[],"variance":0},"ezdxf.xref.ResourceMapper"],"def_extras":{"first_arg":"self"},"fallback":"builtins.function","from_concatenate":false,"implicit":false,"imprecise_arg_kinds":false,"is_bound":false,"is_ellipsis_args":false,"name":"map_resources of BlockRecord","ret_type":{".class":"NoneType"},"type_guard":null,"type_is":null,"unpack_kwargs":false,"variables":[{".class":"TypeVarType","default":{".class":"AnyType","missing_import_name":null,"source_any":null,"type_of_any":4},"fullname":"ezdxf.entities.blockrecord.BlockRecord.Self","id":0,"name":"Self","namespace":"","upper_bound":"ezdxf.entities.blockrecord.BlockRecord","values":[],"variance":0}]}}},"register_resources":{".class":"SymbolTableNode","kind":"Mdef","node":{".class":"FuncDef","abstract_status":0,"arg_kinds":[0,0],"arg_names":["self","registry"],"dataclass_transform_spec":null,"deprecated":null,"flags":["is_trivial_self"],"fullname":"ezdxf.entities.blockrecord.BlockRecord.register_resources","name":"register_resources","type":{".class":"CallableType","arg_kinds":[0,0],"arg_names":["self","registry"],"arg_types":["ezdxf.entities.blockrecord.BlockRecord","ezdxf.xref.Registry"],"def_extras":{"first_arg":"self"},"fallback":"builtins.function","from_concatenate":false,"implicit":false,"imprecise_arg_kinds":false,"is_bound":false,"is_ellipsis_args":false,"name":"register_resources of BlockRecord","ret_type":{".class":"NoneType"},"type_guard":null,"type_is":null,"unpack_kwargs":false,"variables":[]}}},"rename":{".class":"SymbolTableNode","kind":"Mdef","node":{".class":"FuncDef","abstract_status":0,"arg_kinds":[0,0],"arg_names":["self","name"],"dataclass_transform_spec":null,"deprecated":null,"flags":["is_trivial_self"],"fullname":"ezdxf.entities.blockrecord.BlockRecord.rename","name":"rename","type":{".class":"CallableType","arg_kinds":[0,0],"arg_names":["self","name"],"arg_types":["ezdxf.entities.blockrecord.BlockRecord","builtins.str"],"def_extras":{"first_arg":"self"},"fallback":"builtins.function","from_concatenate":false,"implicit":false,"imprecise_arg_kinds":false,"is_bound":false,"is_ellipsis_args":false,"name":"rename of BlockRecord","ret_type":{".class":"NoneType"},"type_guard":null,"type_is":null,"unpack_kwargs":false,"variables":[]}}},"set_block":{".class":"SymbolTableNode","kind":"Mdef","node":{".class":"FuncDef","abstract_status":0,"arg_kinds":[0,0,0],"arg_names":["self","block","endblk"],"dataclass_transform_spec":null,"deprecated":null,"flags":["is_trivial_self"],"fullname":"ezdxf.entities.blockrecord.BlockRecord.set_block","name":"set_block","type":{".class":"CallableType","arg_kinds":[0,0,0],"arg_names":["self","block","endblk"],"arg_types":["ezdxf.entities.blockrecord.BlockRecord","ezdxf.entities.block.Block","ezdxf.entities.block.EndBlk"],"def_extras":{"first_arg":"self"},"fallback":"builtins.function","from_concatenate":false,"implicit":false,"imprecise_arg_kinds":false,"is_bound":false,"is_ellipsis_args":false,"name":"set_block of BlockRecord","ret_type":{".class":"AnyType","missing_import_name":null,"source_any":null,"type_of_any":1},"type_guard":null,"type_is":null,"unpack_kwargs":false,"variables":[]}}},"set_entity_space":{".class":"SymbolTableNode","kind":"Mdef","node":{".class":"FuncDef","abstract_status":0,"arg_kinds":[0,0],"arg_names":["self","entity_space"],"dataclass_transform_spec":null,"deprecated":null,"flags":["is_trivial_self"],"fullname":"ezdxf.entities.blockrecord.BlockRecord.set_entity_space","name":"set_entity_space","type":{".class":"CallableType","arg_kinds":[0,0],"arg_names":["self","entity_space"],"arg_types":["ezdxf.entities.blockrecord.BlockRecord","ezdxf.entitydb.EntitySpace"],"def_extras":{"first_arg":"self"},"fallback":"builtins.function","from_concatenate":false,"implicit":false,"imprecise_arg_kinds":false,"is_bound":false,"is_ellipsis_args":false,"name":"set_entity_space of BlockRecord","ret_type":{".class":"NoneType"},"type_guard":null,"type_is":null,"unpack_kwargs":false,"variables":[]}}},"unlink_entity":{".class":"SymbolTableNode","kind":"Mdef","node":{".class":"FuncDef","abstract_status":0,"arg_kinds":[0,0],"arg_names":["self","entity"],"dataclass_transform_spec":null,"deprecated":null,"flags":["is_trivial_self"],"fullname":"ezdxf.entities.blockrecord.BlockRecord.unlink_entity","name":"unlink_entity","type":{".class":"CallableType","arg_kinds":[0,0],"arg_names":["self","entity"],"arg_types":["ezdxf.entities.blockrecord.BlockRecord","ezdxf.entities.dxfgfx.DXFGraphic"],"def_extras":{"first_arg":"self"},"fallback":"builtins.function","from_concatenate":false,"implicit":false,"imprecise_arg_kinds":false,"is_bound":false,"is_ellipsis_args":false,"name":"unlink_entity of BlockRecord","ret_type":{".class":"NoneType"},"type_guard":null,"type_is":null,"unpack_kwargs":false,"variables":[]}}}},"self_type":{".class":"TypeVarType","default":{".class":"AnyType","missing_import_name":null,"source_any":null,"type_of_any":4},"fullname":"ezdxf.entities.blockrecord.BlockRecord.Self","id":0,"name":"Self","namespace":"","upper_bound":"ezdxf.entities.blockrecord.BlockRecord","values":[],"variance":0},"slots":null,"tuple_type":null,"type_vars":[],"typeddict_type":null}},"DXF12":{".class":"SymbolTableNode","cross_ref":"ezdxf.lldxf.const.DXF12","kind":"Gdef","module_hidden":true,"module_public":false},"DXF2007":{".class":"SymbolTableNode","cross_ref":"ezdxf.lldxf.const.DXF2007","kind":"Gdef","module_hidden":true,"module_public":false},"DXFAttr":{".class":"SymbolTableNode","cross_ref":"ezdxf.lldxf.attributes.DXFAttr","kind":"Gdef","module_hidden":true,"module_public":false},"DXFAttributes":{".class":"SymbolTableNode","cross_ref":"ezdxf.lldxf.attributes.DXFAttributes","kind":"Gdef","module_hidden":true,"module_public":false},"DXFEntity":{".class":"SymbolTableNode","cross_ref":"ezdxf.entities.dxfentity.DXFEntity","kind":"Gdef","module_hidden":true,"module_public":false},"DXFGraphic":{".class":"SymbolTableNode","cross_ref":"ezdxf.entities.dxfgfx.DXFGraphic","kind":"Gdef","module_hidden":true,"module_public":false},"DXFInternalEzdxfError":{".class":"SymbolTableNode","cross_ref":"ezdxf.lldxf.const.DXFInternalEzdxfError","kind":"Gdef","module_hidden":true,"module_public":false},"DXFNamespace":{".class":"SymbolTableNode","cross_ref":"ezdxf.entities.dxfns.DXFNamespace","kind":"Gdef","module_hidden":true,"module_public":false},"DefSubclass":{".class":"SymbolTableNode","cross_ref":"ezdxf.lldxf.attributes.DefSubclass","kind":"Gdef","module_hidden":true,"module_public":false},"EndBlk":{".class":"SymbolTableNode","cross_ref":"ezdxf.entities.block.EndBlk","kind":"Gdef","module_hidden":true,"module_public":false},"EntitySpace":{".class":"SymbolTableNode","cross_ref":"ezdxf.entitydb.EntitySpace","kind":"Gdef","module_hidden":true,"module_public":false},"Optional":{".class":"SymbolTableNode","cross_ref":"typing.Optional","kind":"Gdef","module_hidden":true,"module_public":false},"RETURN_DEFAULT":{".class":"SymbolTableNode","cross_ref":"ezdxf.lldxf.attributes.RETURN_DEFAULT","kind":"Gdef","module_hidden":true,"module_public":false},"SUBCLASS_MARKER":{".class":"SymbolTableNode","cross_ref":"ezdxf.lldxf.const.SUBCLASS_MARKER","kind":"Gdef","module_hidden":true,"module_public":false},"Self":{".class":"SymbolTableNode","cross_ref":"typing.Self","kind":"Gdef","module_hidden":true,"module_public":false},"SubclassProcessor":{".class":"SymbolTableNode","cross_ref":"ezdxf.entities.dxfns.SubclassProcessor","kind":"Gdef","module_hidden":true,"module_public":false},"TYPE_CHECKING":{".class":"SymbolTableNode","cross_ref":"typing.TYPE_CHECKING","kind":"Gdef","module_hidden":true,"module_public":false},"__all__":{".class":"SymbolTableNode","kind":"Gdef","module_public":false,"node":{".class":"Var","flags":["is_inferred","has_explicit_value"],"fullname":"ezdxf.entities.blockrecord.__all__","name":"__all__","setter_type":null,"type":{".class":"Instance","args":["builtins.str"],"extra_attrs":null,"type_ref":"builtins.list"}}},"__annotations__":{".class":"SymbolTableNode","kind":"Gdef","module_public":false,"node":{".class":"Var","flags":["is_ready"],"fullname":"ezdxf.entities.blockrecord.__annotations__","name":"__annotations__","setter_type":null,"type":{".class":"Instance","args":["builtins.str",{".class":"AnyType","missing_import_name":null,"source_any":null,"type_of_any":6}],"extra_attrs":null,"type_ref":"builtins.dict"}}},"__doc__":{".class":"SymbolTableNode","kind":"Gdef","module_public":false,"node":{".class":"Var","flags":["is_ready"],"fullname":"ezdxf.entities.blockrecord.__doc__","name":"__doc__","setter_type":null,"type":"builtins.str"}},"__file__":{".class":"SymbolTableNode","kind":"Gdef","module_public":false,"node":{".class":"Var","flags":["is_ready"],"fullname":"ezdxf.entities.blockrecord.__file__","name":"__file__","setter_type":null,"type":"builtins.str"}},"__name__":{".class":"SymbolTableNode","kind":"Gdef","module_public":false,"node":{".class":"Var","flags":["is_ready"],"fullname":"ezdxf.entities.blockrecord.__name__","name":"__name__","setter_type":null,"type":"builtins.str"}},"__package__":{".class":"SymbolTableNode","kind":"Gdef","module_public":false,"node":{".class":"Var","flags":["is_ready"],"fullname":"ezdxf.entities.blockrecord.__package__","name":"__package__","setter_type":null,"type":"builtins.str"}},"__spec__":{".class":"SymbolTableNode","kind":"Gdef","module_public":false,"node":{".class":"Var","flags":["is_ready"],"fullname":"ezdxf.entities.blockrecord.__spec__","name":"__spec__","setter_type":null,"type":"_frozen_importlib.ModuleSpec"}},"acdb_blockrec":{".class":"SymbolTableNode","kind":"Gdef","module_public":false,"node":{".class":"Var","flags":["is_inferred","has_explicit_value"],"fullname":"ezdxf.entities.blockrecord.acdb_blockrec","name":"acdb_blockrec","setter_type":null,"type":{".class":"TupleType","implicit":false,"items":[{".class":"UnionType","items":["builtins.str",{".class":"NoneType"}],"uses_pep604_syntax":false},{".class":"Instance","args":["builtins.str","ezdxf.lldxf.attributes.DXFAttr"],"extra_attrs":null,"type_ref":"builtins.dict"}],"partial_fallback":"ezdxf.lldxf.attributes.DefSubclass"}}},"acdb_blockrec_group_codes":{".class":"SymbolTableNode","kind":"Gdef","module_public":false,"node":{".class":"Var","flags":["is_inferred","has_explicit_value"],"fullname":"ezdxf.entities.blockrecord.acdb_blockrec_group_codes","name":"acdb_blockrec_group_codes","setter_type":null,"type":{".class":"Instance","args":["builtins.int",{".class":"UnionType","items":["builtins.str",{".class":"Instance","args":["builtins.str"],"extra_attrs":null,"type_ref":"builtins.list"}],"uses_pep604_syntax":false}],"extra_attrs":null,"type_ref":"builtins.dict"}}},"acdb_symbol_table_record":{".class":"SymbolTableNode","cross_ref":"ezdxf.entities.layer.acdb_symbol_table_record","kind":"Gdef","module_hidden":true,"module_public":false},"annotations":{".class":"SymbolTableNode","cross_ref":"__future__.annotations","kind":"Gdef","module_hidden":true,"module_public":false},"base_class":{".class":"SymbolTableNode","cross_ref":"ezdxf.entities.dxfentity.base_class","kind":"Gdef","module_hidden":true,"module_public":false},"group_code_mapping":{".class":"SymbolTableNode","cross_ref":"ezdxf.lldxf.attributes.group_code_mapping","kind":"Gdef","module_hidden":true,"module_public":false},"logger":{".class":"SymbolTableNode","kind":"Gdef","module_public":false,"node":{".class":"Var","flags":["is_inferred","has_explicit_value"],"fullname":"ezdxf.entities.blockrecord.logger","name":"logger","setter_type":null,"type":"logging.Logger"}},"logging":{".class":"SymbolTableNode","cross_ref":"logging","kind":"Gdef","module_hidden":true,"module_public":false},"register_entity":{".class":"SymbolTableNode","cross_ref":"ezdxf.entities.factory.register_entity","kind":"Gdef","module_hidden":true,"module_public":false},"validator":{".class":"SymbolTableNode","cross_ref":"ezdxf.lldxf.validator","kind":"Gdef","module_hidden":true,"module_public":false},"xref":{".class":"SymbolTableNode","cross_ref":"ezdxf.xref","kind":"Gdef","module_hidden":true,"module_public":false}},"path":"/home/hemang/myenv313/lib/python3.13/site-packages/ezdxf/entities/blockrecord.py"}