{".class":"MypyFile","_fullname":"ezdxf.entities.subentity","future_import_flags":["annotations"],"is_partial_stub_package":false,"is_stub":false,"names":{".class":"SymbolTable","Callable":{".class":"SymbolTableNode","cross_ref":"typing.Callable","kind":"Gdef","module_hidden":true,"module_public":false},"DXFEntity":{".class":"SymbolTableNode","cross_ref":"ezdxf.entities.dxfentity.DXFEntity","kind":"Gdef","module_hidden":true,"module_public":false},"DXFGraphic":{".class":"SymbolTableNode","cross_ref":"ezdxf.entities.dxfgfx.DXFGraphic","kind":"Gdef","module_hidden":true,"module_public":false},"Drawing":{".class":"SymbolTableNode","cross_ref":"ezdxf.document.Drawing","kind":"Gdef","module_hidden":true,"module_public":false},"EntityDB":{".class":"SymbolTableNode","cross_ref":"ezdxf.entitydb.EntityDB","kind":"Gdef","module_hidden":true,"module_public":false},"Iterable":{".class":"SymbolTableNode","cross_ref":"typing.Iterable","kind":"Gdef","module_hidden":true,"module_public":false},"LINKED_ENTITIES":{".class":"SymbolTableNode","kind":"Gdef","module_public":false,"node":{".class":"Var","flags":["is_inferred","has_explicit_value"],"fullname":"ezdxf.entities.subentity.LINKED_ENTITIES","name":"LINKED_ENTITIES","setter_type":null,"type":{".class":"Instance","args":["builtins.str","builtins.str"],"extra_attrs":null,"type_ref":"builtins.dict"}}},"LinkedEntities":{".class":"SymbolTableNode","kind":"Gdef","node":{".class":"TypeInfo","_promote":[],"abstract_attributes":[],"alt_promote":null,"bases":["ezdxf.entities.dxfgfx.DXFGraphic"],"dataclass_transform_spec":null,"declared_metaclass":null,"defn":{".class":"ClassDef","fullname":"ezdxf.entities.subentity.LinkedEntities","name":"LinkedEntities","type_vars":[]},"deletable_attributes":[],"deprecated":null,"flags":[],"fullname":"ezdxf.entities.subentity.LinkedEntities","has_param_spec_type":false,"metaclass_type":null,"metadata":{},"module_name":"ezdxf.entities.subentity","mro":["ezdxf.entities.subentity.LinkedEntities","ezdxf.entities.dxfgfx.DXFGraphic","ezdxf.entities.dxfentity.DXFEntity","builtins.object"],"names":{".class":"SymbolTable","__init__":{".class":"SymbolTableNode","kind":"Mdef","node":{".class":"FuncDef","abstract_status":0,"arg_kinds":[0],"arg_names":["self"],"dataclass_transform_spec":null,"deprecated":null,"flags":["is_trivial_self"],"fullname":"ezdxf.entities.subentity.LinkedEntities.__init__","name":"__init__","type":{".class":"CallableType","arg_kinds":[0],"arg_names":["self"],"arg_types":["ezdxf.entities.subentity.LinkedEntities"],"def_extras":{"first_arg":"self"},"fallback":"builtins.function","from_concatenate":false,"implicit":false,"imprecise_arg_kinds":false,"is_bound":false,"is_ellipsis_args":false,"name":"__init__ of LinkedEntities","ret_type":{".class":"NoneType"},"type_guard":null,"type_is":null,"unpack_kwargs":false,"variables":[]}}},"_sub_entities":{".class":"SymbolTableNode","implicit":true,"kind":"Mdef","node":{".class":"Var","flags":["explicit_self_type","is_ready","is_inferred"],"fullname":"ezdxf.entities.subentity.LinkedEntities._sub_entities","name":"_sub_entities","setter_type":null,"type":{".class":"Instance","args":["ezdxf.entities.dxfgfx.DXFGraphic"],"extra_attrs":null,"type_ref":"builtins.list"}}},"add_sub_entities_to_entitydb":{".class":"SymbolTableNode","kind":"Mdef","node":{".class":"FuncDef","abstract_status":0,"arg_kinds":[0,0],"arg_names":["self","db"],"dataclass_transform_spec":null,"deprecated":null,"flags":["is_trivial_self"],"fullname":"ezdxf.entities.subentity.LinkedEntities.add_sub_entities_to_entitydb","name":"add_sub_entities_to_entitydb","type":{".class":"CallableType","arg_kinds":[0,0],"arg_names":["self","db"],"arg_types":["ezdxf.entities.subentity.LinkedEntities","ezdxf.entitydb.EntityDB"],"def_extras":{"first_arg":"self"},"fallback":"builtins.function","from_concatenate":false,"implicit":false,"imprecise_arg_kinds":false,"is_bound":false,"is_ellipsis_args":false,"name":"add_sub_entities_to_entitydb of LinkedEntities","ret_type":{".class":"NoneType"},"type_guard":null,"type_is":null,"unpack_kwargs":false,"variables":[]}}},"all_sub_entities":{".class":"SymbolTableNode","kind":"Mdef","node":{".class":"FuncDef","abstract_status":0,"arg_kinds":[0],"arg_names":["self"],"dataclass_transform_spec":null,"deprecated":null,"flags":["is_trivial_self"],"fullname":"ezdxf.entities.subentity.LinkedEntities.all_sub_entities","name":"all_sub_entities","type":{".class":"CallableType","arg_kinds":[0],"arg_names":["self"],"arg_types":["ezdxf.entities.subentity.LinkedEntities"],"def_extras":{"first_arg":"self"},"fallback":"builtins.function","from_concatenate":false,"implicit":false,"imprecise_arg_kinds":false,"is_bound":false,"is_ellipsis_args":false,"name":"all_sub_entities of LinkedEntities","ret_type":{".class":"Instance","args":["ezdxf.entities.dxfentity.DXFEntity"],"extra_attrs":null,"type_ref":"typing.Iterable"},"type_guard":null,"type_is":null,"unpack_kwargs":false,"variables":[]}}},"copy_data":{".class":"SymbolTableNode","kind":"Mdef","node":{".class":"FuncDef","abstract_status":0,"arg_kinds":[0,0,1],"arg_names":["self","entity","copy_strategy"],"dataclass_transform_spec":null,"deprecated":null,"flags":[],"fullname":"ezdxf.entities.subentity.LinkedEntities.copy_data","name":"copy_data","type":{".class":"CallableType","arg_kinds":[0,0,1],"arg_names":["self","entity","copy_strategy"],"arg_types":[{".class":"TypeVarType","default":{".class":"AnyType","missing_import_name":null,"source_any":null,"type_of_any":4},"fullname":"ezdxf.entities.subentity.LinkedEntities.Self","id":0,"name":"Self","namespace":"","upper_bound":"ezdxf.entities.subentity.LinkedEntities","values":[],"variance":0},{".class":"TypeVarType","default":{".class":"AnyType","missing_import_name":null,"source_any":null,"type_of_any":4},"fullname":"ezdxf.entities.subentity.LinkedEntities.Self","id":0,"name":"Self","namespace":"","upper_bound":"ezdxf.entities.subentity.LinkedEntities","values":[],"variance":0},{".class":"AnyType","missing_import_name":null,"source_any":null,"type_of_any":1}],"def_extras":{"first_arg":"self"},"fallback":"builtins.function","from_concatenate":false,"implicit":false,"imprecise_arg_kinds":false,"is_bound":false,"is_ellipsis_args":false,"name":"copy_data of LinkedEntities","ret_type":{".class":"NoneType"},"type_guard":null,"type_is":null,"unpack_kwargs":false,"variables":[{".class":"TypeVarType","default":{".class":"AnyType","missing_import_name":null,"source_any":null,"type_of_any":4},"fullname":"ezdxf.entities.subentity.LinkedEntities.Self","id":0,"name":"Self","namespace":"","upper_bound":"ezdxf.entities.subentity.LinkedEntities","values":[],"variance":0}]}}},"destroy":{".class":"SymbolTableNode","kind":"Mdef","node":{".class":"FuncDef","abstract_status":0,"arg_kinds":[0],"arg_names":["self"],"dataclass_transform_spec":null,"deprecated":null,"flags":["is_trivial_self"],"fullname":"ezdxf.entities.subentity.LinkedEntities.destroy","name":"destroy","type":{".class":"CallableType","arg_kinds":[0],"arg_names":["self"],"arg_types":["ezdxf.entities.subentity.LinkedEntities"],"def_extras":{"first_arg":"self"},"fallback":"builtins.function","from_concatenate":false,"implicit":false,"imprecise_arg_kinds":false,"is_bound":false,"is_ellipsis_args":false,"name":"destroy of LinkedEntities","ret_type":{".class":"NoneType"},"type_guard":null,"type_is":null,"unpack_kwargs":false,"variables":[]}}},"link_entity":{".class":"SymbolTableNode","kind":"Mdef","node":{".class":"FuncDef","abstract_status":0,"arg_kinds":[0,0],"arg_names":["self","entity"],"dataclass_transform_spec":null,"deprecated":null,"flags":["is_trivial_self"],"fullname":"ezdxf.entities.subentity.LinkedEntities.link_entity","name":"link_entity","type":{".class":"CallableType","arg_kinds":[0,0],"arg_names":["self","entity"],"arg_types":["ezdxf.entities.subentity.LinkedEntities","ezdxf.entities.dxfentity.DXFEntity"],"def_extras":{"first_arg":"self"},"fallback":"builtins.function","from_concatenate":false,"implicit":false,"imprecise_arg_kinds":false,"is_bound":false,"is_ellipsis_args":false,"name":"link_entity of LinkedEntities","ret_type":{".class":"NoneType"},"type_guard":null,"type_is":null,"unpack_kwargs":false,"variables":[]}}},"link_seqend":{".class":"SymbolTableNode","kind":"Mdef","node":{".class":"FuncDef","abstract_status":0,"arg_kinds":[0,0],"arg_names":["self","seqend"],"dataclass_transform_spec":null,"deprecated":null,"flags":["is_trivial_self"],"fullname":"ezdxf.entities.subentity.LinkedEntities.link_seqend","name":"link_seqend","type":{".class":"CallableType","arg_kinds":[0,0],"arg_names":["self","seqend"],"arg_types":["ezdxf.entities.subentity.LinkedEntities","ezdxf.entities.dxfentity.DXFEntity"],"def_extras":{"first_arg":"self"},"fallback":"builtins.function","from_concatenate":false,"implicit":false,"imprecise_arg_kinds":false,"is_bound":false,"is_ellipsis_args":false,"name":"link_seqend of LinkedEntities","ret_type":{".class":"NoneType"},"type_guard":null,"type_is":null,"unpack_kwargs":false,"variables":[]}}},"map_resources":{".class":"SymbolTableNode","kind":"Mdef","node":{".class":"FuncDef","abstract_status":0,"arg_kinds":[0,0,0],"arg_names":["self","clone","mapping"],"dataclass_transform_spec":null,"deprecated":null,"flags":[],"fullname":"ezdxf.entities.subentity.LinkedEntities.map_resources","name":"map_resources","type":{".class":"CallableType","arg_kinds":[0,0,0],"arg_names":["self","clone","mapping"],"arg_types":[{".class":"TypeVarType","default":{".class":"AnyType","missing_import_name":null,"source_any":null,"type_of_any":4},"fullname":"ezdxf.entities.subentity.LinkedEntities.Self","id":0,"name":"Self","namespace":"","upper_bound":"ezdxf.entities.subentity.LinkedEntities","values":[],"variance":0},{".class":"TypeVarType","default":{".class":"AnyType","missing_import_name":null,"source_any":null,"type_of_any":4},"fullname":"ezdxf.entities.subentity.LinkedEntities.Self","id":0,"name":"Self","namespace":"","upper_bound":"ezdxf.entities.subentity.LinkedEntities","values":[],"variance":0},"ezdxf.xref.ResourceMapper"],"def_extras":{"first_arg":"self"},"fallback":"builtins.function","from_concatenate":false,"implicit":false,"imprecise_arg_kinds":false,"is_bound":false,"is_ellipsis_args":false,"name":"map_resources of LinkedEntities","ret_type":{".class":"NoneType"},"type_guard":null,"type_is":null,"unpack_kwargs":false,"variables":[{".class":"TypeVarType","default":{".class":"AnyType","missing_import_name":null,"source_any":null,"type_of_any":4},"fullname":"ezdxf.entities.subentity.LinkedEntities.Self","id":0,"name":"Self","namespace":"","upper_bound":"ezdxf.entities.subentity.LinkedEntities","values":[],"variance":0}]}}},"new_seqend":{".class":"SymbolTableNode","kind":"Mdef","node":{".class":"FuncDef","abstract_status":0,"arg_kinds":[0],"arg_names":["self"],"dataclass_transform_spec":null,"deprecated":null,"flags":[],"fullname":"ezdxf.entities.subentity.LinkedEntities.new_seqend","name":"new_seqend","type":null}},"post_bind_hook":{".class":"SymbolTableNode","kind":"Mdef","node":{".class":"FuncDef","abstract_status":0,"arg_kinds":[0],"arg_names":["self"],"dataclass_transform_spec":null,"deprecated":null,"flags":[],"fullname":"ezdxf.entities.subentity.LinkedEntities.post_bind_hook","name":"post_bind_hook","type":null}},"process_sub_entities":{".class":"SymbolTableNode","kind":"Mdef","node":{".class":"FuncDef","abstract_status":0,"arg_kinds":[0,0],"arg_names":["self","func"],"dataclass_transform_spec":null,"deprecated":null,"flags":["is_trivial_self"],"fullname":"ezdxf.entities.subentity.LinkedEntities.process_sub_entities","name":"process_sub_entities","type":{".class":"CallableType","arg_kinds":[0,0],"arg_names":["self","func"],"arg_types":["ezdxf.entities.subentity.LinkedEntities",{".class":"CallableType","arg_kinds":[0],"arg_names":[null],"arg_types":["ezdxf.entities.dxfentity.DXFEntity"],"def_extras":{},"fallback":"builtins.function","from_concatenate":false,"implicit":false,"imprecise_arg_kinds":false,"is_bound":false,"is_ellipsis_args":false,"name":null,"ret_type":{".class":"NoneType"},"type_guard":null,"type_is":null,"unpack_kwargs":false,"variables":[]}],"def_extras":{"first_arg":"self"},"fallback":"builtins.function","from_concatenate":false,"implicit":false,"imprecise_arg_kinds":false,"is_bound":false,"is_ellipsis_args":false,"name":"process_sub_entities of LinkedEntities","ret_type":{".class":"AnyType","missing_import_name":null,"source_any":null,"type_of_any":1},"type_guard":null,"type_is":null,"unpack_kwargs":false,"variables":[]}}},"register_resources":{".class":"SymbolTableNode","kind":"Mdef","node":{".class":"FuncDef","abstract_status":0,"arg_kinds":[0,0],"arg_names":["self","registry"],"dataclass_transform_spec":null,"deprecated":null,"flags":["is_trivial_self"],"fullname":"ezdxf.entities.subentity.LinkedEntities.register_resources","name":"register_resources","type":{".class":"CallableType","arg_kinds":[0,0],"arg_names":["self","registry"],"arg_types":["ezdxf.entities.subentity.LinkedEntities","ezdxf.xref.Registry"],"def_extras":{"first_arg":"self"},"fallback":"builtins.function","from_concatenate":false,"implicit":false,"imprecise_arg_kinds":false,"is_bound":false,"is_ellipsis_args":false,"name":"register_resources of LinkedEntities","ret_type":{".class":"NoneType"},"type_guard":null,"type_is":null,"unpack_kwargs":false,"variables":[]}}},"remove_dependencies":{".class":"SymbolTableNode","kind":"Mdef","node":{".class":"FuncDef","abstract_status":0,"arg_kinds":[0,1],"arg_names":["self","other"],"dataclass_transform_spec":null,"deprecated":null,"flags":["is_trivial_self"],"fullname":"ezdxf.entities.subentity.LinkedEntities.remove_dependencies","name":"remove_dependencies","type":{".class":"CallableType","arg_kinds":[0,1],"arg_names":["self","other"],"arg_types":["ezdxf.entities.subentity.LinkedEntities",{".class":"UnionType","items":["ezdxf.document.Drawing",{".class":"NoneType"}],"uses_pep604_syntax":false}],"def_extras":{"first_arg":"self"},"fallback":"builtins.function","from_concatenate":false,"implicit":false,"imprecise_arg_kinds":false,"is_bound":false,"is_ellipsis_args":false,"name":"remove_dependencies of LinkedEntities","ret_type":{".class":"AnyType","missing_import_name":null,"source_any":null,"type_of_any":1},"type_guard":null,"type_is":null,"unpack_kwargs":false,"variables":[]}}},"seqend":{".class":"SymbolTableNode","implicit":true,"kind":"Mdef","node":{".class":"Var","flags":["explicit_self_type","is_ready","is_inferred"],"fullname":"ezdxf.entities.subentity.LinkedEntities.seqend","name":"seqend","setter_type":null,"type":{".class":"UnionType","items":["ezdxf.entities.dxfgfx.SeqEnd",{".class":"NoneType"}],"uses_pep604_syntax":false}}},"set_owner":{".class":"SymbolTableNode","kind":"Mdef","node":{".class":"FuncDef","abstract_status":0,"arg_kinds":[0,0,1],"arg_names":["self","owner","paperspace"],"dataclass_transform_spec":null,"deprecated":null,"flags":["is_trivial_self"],"fullname":"ezdxf.entities.subentity.LinkedEntities.set_owner","name":"set_owner","type":{".class":"CallableType","arg_kinds":[0,0,1],"arg_names":["self","owner","paperspace"],"arg_types":["ezdxf.entities.subentity.LinkedEntities",{".class":"UnionType","items":["builtins.str",{".class":"NoneType"}],"uses_pep604_syntax":false},"builtins.int"],"def_extras":{"first_arg":"self"},"fallback":"builtins.function","from_concatenate":false,"implicit":false,"imprecise_arg_kinds":false,"is_bound":false,"is_ellipsis_args":false,"name":"set_owner of LinkedEntities","ret_type":{".class":"AnyType","missing_import_name":null,"source_any":null,"type_of_any":1},"type_guard":null,"type_is":null,"unpack_kwargs":false,"variables":[]}}},"take_ownership":{".class":"SymbolTableNode","kind":"Mdef","node":{".class":"FuncDef","abstract_status":0,"arg_kinds":[0],"arg_names":["self"],"dataclass_transform_spec":null,"deprecated":null,"flags":[],"fullname":"ezdxf.entities.subentity.LinkedEntities.take_ownership","name":"take_ownership","type":null}}},"self_type":{".class":"TypeVarType","default":{".class":"AnyType","missing_import_name":null,"source_any":null,"type_of_any":4},"fullname":"ezdxf.entities.subentity.LinkedEntities.Self","id":0,"name":"Self","namespace":"","upper_bound":"ezdxf.entities.subentity.LinkedEntities","values":[],"variance":0},"slots":null,"tuple_type":null,"type_vars":[],"typeddict_type":null}},"Optional":{".class":"SymbolTableNode","cross_ref":"typing.Optional","kind":"Gdef","module_hidden":true,"module_public":false},"Self":{".class":"SymbolTableNode","cross_ref":"typing.Self","kind":"Gdef","module_hidden":true,"module_public":false},"SeqEnd":{".class":"SymbolTableNode","cross_ref":"ezdxf.entities.dxfgfx.SeqEnd","kind":"Gdef","module_hidden":true,"module_public":false},"TYPE_CHECKING":{".class":"SymbolTableNode","cross_ref":"typing.TYPE_CHECKING","kind":"Gdef","module_hidden":true,"module_public":false},"__all__":{".class":"SymbolTableNode","kind":"Gdef","module_public":false,"node":{".class":"Var","flags":["is_inferred","has_explicit_value"],"fullname":"ezdxf.entities.subentity.__all__","name":"__all__","setter_type":null,"type":{".class":"Instance","args":["builtins.str"],"extra_attrs":null,"type_ref":"builtins.list"}}},"__annotations__":{".class":"SymbolTableNode","kind":"Gdef","module_public":false,"node":{".class":"Var","flags":["is_ready"],"fullname":"ezdxf.entities.subentity.__annotations__","name":"__annotations__","setter_type":null,"type":{".class":"Instance","args":["builtins.str",{".class":"AnyType","missing_import_name":null,"source_any":null,"type_of_any":6}],"extra_attrs":null,"type_ref":"builtins.dict"}}},"__doc__":{".class":"SymbolTableNode","kind":"Gdef","module_public":false,"node":{".class":"Var","flags":["is_ready"],"fullname":"ezdxf.entities.subentity.__doc__","name":"__doc__","setter_type":null,"type":"builtins.str"}},"__file__":{".class":"SymbolTableNode","kind":"Gdef","module_public":false,"node":{".class":"Var","flags":["is_ready"],"fullname":"ezdxf.entities.subentity.__file__","name":"__file__","setter_type":null,"type":"builtins.str"}},"__name__":{".class":"SymbolTableNode","kind":"Gdef","module_public":false,"node":{".class":"Var","flags":["is_ready"],"fullname":"ezdxf.entities.subentity.__name__","name":"__name__","setter_type":null,"type":"builtins.str"}},"__package__":{".class":"SymbolTableNode","kind":"Gdef","module_public":false,"node":{".class":"Var","flags":["is_ready"],"fullname":"ezdxf.entities.subentity.__package__","name":"__package__","setter_type":null,"type":"builtins.str"}},"__spec__":{".class":"SymbolTableNode","kind":"Gdef","module_public":false,"node":{".class":"Var","flags":["is_ready"],"fullname":"ezdxf.entities.subentity.__spec__","name":"__spec__","setter_type":null,"type":"_frozen_importlib.ModuleSpec"}},"annotations":{".class":"SymbolTableNode","cross_ref":"__future__.annotations","kind":"Gdef","module_hidden":true,"module_public":false},"const":{".class":"SymbolTableNode","cross_ref":"ezdxf.lldxf.const","kind":"Gdef","module_hidden":true,"module_public":false},"default_copy":{".class":"SymbolTableNode","cross_ref":"ezdxf.entities.copy.default_copy","kind":"Gdef","module_hidden":true,"module_public":false},"entity_linker":{".class":"SymbolTableNode","kind":"Gdef","node":{".class":"FuncDef","abstract_status":0,"arg_kinds":[],"arg_names":[],"dataclass_transform_spec":null,"deprecated":null,"flags":[],"fullname":"ezdxf.entities.subentity.entity_linker","name":"entity_linker","type":{".class":"CallableType","arg_kinds":[],"arg_names":[],"arg_types":[],"def_extras":{"first_arg":null},"fallback":"builtins.function","from_concatenate":false,"implicit":false,"imprecise_arg_kinds":false,"is_bound":false,"is_ellipsis_args":false,"name":"entity_linker","ret_type":{".class":"CallableType","arg_kinds":[0],"arg_names":[null],"arg_types":["ezdxf.entities.dxfentity.DXFEntity"],"def_extras":{},"fallback":"builtins.function","from_concatenate":false,"implicit":false,"imprecise_arg_kinds":false,"is_bound":false,"is_ellipsis_args":false,"name":null,"ret_type":"builtins.bool","type_guard":null,"type_is":null,"unpack_kwargs":false,"variables":[]},"type_guard":null,"type_is":null,"unpack_kwargs":false,"variables":[]}}},"factory":{".class":"SymbolTableNode","cross_ref":"ezdxf.entities.factory","kind":"Gdef","module_hidden":true,"module_public":false},"logger":{".class":"SymbolTableNode","kind":"Gdef","module_public":false,"node":{".class":"Var","flags":["is_inferred","has_explicit_value"],"fullname":"ezdxf.entities.subentity.logger","name":"logger","setter_type":null,"type":"logging.Logger"}},"logging":{".class":"SymbolTableNode","cross_ref":"logging","kind":"Gdef","module_hidden":true,"module_public":false},"xref":{".class":"SymbolTableNode","cross_ref":"ezdxf.xref","kind":"Gdef","module_hidden":true,"module_public":false}},"path":"/home/hemang/myenv313/lib/python3.13/site-packages/ezdxf/entities/subentity.py"}